{
	"info": {
		"_postman_id": "69064559-7492-452e-8fc3-af04af13467b",
		"name": "Udatube Serverless",
		"schema": "https://schema.getpostman.com/json/collection/v2.1.0/collection.json"
	},
	"item": [
		{
			"name": "Create video",
			"request": {
				"method": "POST",
				"header": [
					{
						"key": "Content-Type",
						"value": "application/json",
						"type": "text"
					},
					{
						"key": "Authorization",
						"value": "Bearer {{authToken}}",
						"type": "text"
					}
				],
				"body": {
					"mode": "raw",
					"raw": "{\n\t\"name\": \"top of lionel messi\",\n    \"description\": \"video about lionel messi\"\n}",
					"options": {
						"raw": {
							"language": "json"
						}
					}
				},
				"url": {
					"raw": "https://{{apiId}}.execute-api.us-east-1.amazonaws.com/dev/videos",
					"protocol": "https",
					"host": [
						"{{apiId}}",
						"execute-api",
						"us-east-1",
						"amazonaws",
						"com"
					],
					"path": [
						"dev",
						"videos"
					]
				}
			},
			"response": []
		},
		{
			"name": "Update video",
			"request": {
				"method": "PATCH",
				"header": [
					{
						"key": "Content-Type",
						"value": "application/json",
						"type": "text"
					},
					{
						"key": "Authorization",
						"value": "Bearer {{authToken}}",
						"type": "text"
					}
				],
				"body": {
					"mode": "raw",
					"raw": "{\n\t\"name\": \"7 ballons d'or messi\",\n    \"description\": \"7 ballons d'or messi\"\n}"
				},
				"url": {
					"raw": "https://{{apiId}}.execute-api.us-east-1.amazonaws.com/dev/videos/2ccdd76e-6e58-4d52-97cb-912950d3c1d9",
					"protocol": "https",
					"host": [
						"{{apiId}}",
						"execute-api",
						"us-east-1",
						"amazonaws",
						"com"
					],
					"path": [
						"dev",
						"videos",
						"2ccdd76e-6e58-4d52-97cb-912950d3c1d9"
					]
				}
			},
			"response": []
		},
		{
			"name": "Delete video",
			"request": {
				"method": "DELETE",
				"header": [
					{
						"key": "conten",
						"value": "application/json",
						"type": "text"
					},
					{
						"key": "Authorization",
						"value": "Bearer {{authToken}}",
						"type": "text"
					}
				],
				"url": {
					"raw": "https://{{apiId}}.execute-api.us-east-1.amazonaws.com/dev/videos/083ffa45-2263-4193-8d5e-9ed39ee1f76d",
					"protocol": "https",
					"host": [
						"{{apiId}}",
						"execute-api",
						"us-east-1",
						"amazonaws",
						"com"
					],
					"path": [
						"dev",
						"videos",
						"083ffa45-2263-4193-8d5e-9ed39ee1f76d"
					]
				}
			},
			"response": []
		},
		{
			"name": "Get my-videos",
			"request": {
				"method": "GET",
				"header": [
					{
						"key": "Content-Type",
						"value": "application/json",
						"type": "text"
					},
					{
						"key": "Authorization",
						"value": "Bearer {{authToken}}",
						"type": "text"
					}
				],
				"url": {
					"raw": "https://{{apiId}}.execute-api.us-east-1.amazonaws.com/dev/my-videos",
					"protocol": "https",
					"host": [
						"{{apiId}}",
						"execute-api",
						"us-east-1",
						"amazonaws",
						"com"
					],
					"path": [
						"dev",
						"my-videos"
					]
				}
			},
			"response": []
		},
		{
			"name": "Get attachment URL",
			"request": {
				"method": "POST",
				"header": [
					{
						"key": "Authorization",
						"value": "Bearer {{authToken}}",
						"type": "text"
					}
				],
				"body": {
					"mode": "raw",
					"raw": ""
				},
				"url": {
					"raw": "https://{{apiId}}.execute-api.us-east-1.amazonaws.com/dev/videos/0833fc76-18c5-4167-88d3-c8c6a5ad09a4/attachment",
					"protocol": "https",
					"host": [
						"{{apiId}}",
						"execute-api",
						"us-east-1",
						"amazonaws",
						"com"
					],
					"path": [
						"dev",
						"videos",
						"0833fc76-18c5-4167-88d3-c8c6a5ad09a4",
						"attachment"
					]
				}
			},
			"response": []
		}
	],
	"event": [
		{
			"listen": "prerequest",
			"script": {
				"type": "text/javascript",
				"exec": [
					""
				]
			}
		},
		{
			"listen": "test",
			"script": {
				"type": "text/javascript",
				"exec": [
					""
				]
			}
		}
	],
	"variable": [
		{
			"key": "apiId",
			"value": ""
		},
		{
			"key": "authToken",
			"value": ""
		}
	]
}